my_exes/__init__.py
my_exes/csv_logger.py
my_exes/my_ex.py
my_exes-0.1.3.dist-info/WHEEL
my_exes-0.1.3.dist-info/METADATA
my_exes-0.1.3.dist-info/RECORD
