Metadata-Version: 2.3
Name: my-exes
Version: 0.1.3
Summary: A simple package to log your DL experiments
Author: Mehdi Seifi
Author-email: Mehdi Seifi <mehdiseifi@gmail.com>
Requires-Dist: crc32c>=2.8
Requires-Dist: hydra-core>=1.3.2
Requires-Dist: pandas>=2.3.3
Requires-Dist: pyyaml>=6.0.3
Requires-Dist: tensorboard>=2.18.0
Requires-Dist: tensorboardx>=2.6.4
Requires-Dist: torch>=2.0
Requires-Python: >=3.10
